knowledgeai/__init__.py
knowledgeai/client/__init__.py
knowledgeai/client/admin.py
knowledgeai/client/client.py
knowledgeai/client/schema.py
knowledgeai_client-0.7.0.dist-info/LICENSE
knowledgeai_client-0.7.0.dist-info/METADATA
knowledgeai_client-0.7.0.dist-info/WHEEL
knowledgeai_client-0.7.0.dist-info/RECORD
