Metadata-Version: 2.1
Name: knowledgeai-client
Version: 0.7.0
Summary: A python client for the Avvia Intelligence - Knowledge AI Rest API
Home-page: https://github.com/arvato-systems-aila-solutions/KnowledgeAI-Python-Client
License: MIT
Keywords: AI,Knowledge Retrieval,arvato systems,avvia intelligence,knowledgeai
Author: Arvato Systems
Requires-Python: >=3.11
Classifier: License :: OSI Approved :: MIT License
Classifier: Programming Language :: Python :: 3
Classifier: Programming Language :: Python :: 3.11
Classifier: Programming Language :: Python :: 3.12
Requires-Dist: httpx (==0.27.0)
Requires-Dist: pydantic (==2.7.0)
Requires-Dist: pydantic-settings (==2.2.1)
Requires-Dist: python-iso639 (==2024.2.7)
Requires-Dist: python-magic (==0.4.27)
Requires-Dist: tqdm (==4.66.2)
